MANIFEST.in
README.rst
setup.cfg
setup.py
requirements/package.txt
twitter_bot/__init__.py
twitter_bot/settings.py
twitter_bot/twitter_bot.py
twitter_bot/messages/__init__.py
twitter_bot/messages/base.py
twitter_bot/messages/hello_world.py
twitter_bot/messages/markov_chain.py
twitter_bot/since_id/__init__.py
twitter_bot/since_id/base_provider.py
twitter_bot/since_id/file_system_provider.py
twitter_bot/since_id/redis_provider.py
twitterbot.egg-info/PKG-INFO
twitterbot.egg-info/SOURCES.txt
twitterbot.egg-info/dependency_links.txt
twitterbot.egg-info/requires.txt
twitterbot.egg-info/top_level.txt