Metadata-Version: 1.1
Name: twitterbot
Version: 0.3.4
Summary: Configurable bot that replies to mentions and posts messages to twitter
Home-page: https://github.com/jessamynsmith/twitterbot
Author: Jessamyn Smith
Author-email: jessamyn.smith@gmail.com
License: MIT
Download-URL: https://github.com/jessamynsmith/twitterbot/archive/v0.3.4.tar.gz
Keywords: twitter,bot,web 2.0,command-line tools
Platform: UNKNOWN
Classifier: Development Status :: 4 - Beta
Classifier: Environment :: Console
Classifier: Intended Audience :: Developers
Classifier: Intended Audience :: End Users/Desktop
Classifier: Natural Language :: English
Classifier: Operating System :: OS Independent
Classifier: Programming Language :: Python
Classifier: Programming Language :: Python :: 2.6
Classifier: Programming Language :: Python :: 2.7
Classifier: Programming Language :: Python :: 3.2
Classifier: Programming Language :: Python :: 3.3
Classifier: Programming Language :: Python :: 3.4
Classifier: Programming Language :: Python :: 3.5
Classifier: Programming Language :: Python :: 3.6
Classifier: Programming Language :: Python :: 3.7
Classifier: License :: OSI Approved :: MIT License
Classifier: Topic :: Internet :: WWW/HTTP :: Dynamic Content :: CGI Tools/Libraries
Classifier: Topic :: Software Development
Classifier: Topic :: Utilities
Classifier: License :: OSI Approved :: MIT License
